pybloomd.py
setup.py
pybloomd.egg-info/PKG-INFO
pybloomd.egg-info/SOURCES.txt
pybloomd.egg-info/dependency_links.txt
pybloomd.egg-info/top_level.txt