Metadata-Version: 1.0
Name: pybloomd
Version: 0.4.6
Summary: Client library to interface with multiple bloomd servers
Home-page: https://github.com/kiip/bloom-python-driver/
Author: Armon Dadgar
Author-email: biz@kiip.me
License: MIT License
Keywords: bloom,filter,client,bloomd
Platform: UNKNOWN
Classifier: Development Status :: 4 - Beta
Classifier: Intended Audience :: Developers
Classifier: License :: OSI Approved :: MIT License
Classifier: Operating System :: POSIX
Classifier: Programming Language :: Python
Classifier: Topic :: Database
Classifier: Topic :: Internet
Classifier: Topic :: Software Development :: Libraries
